setup.py
distributions_dsnd/Binomialdistribution.py
distributions_dsnd/Gaussiandistribution.py
distributions_dsnd/Generaldistribution.py
distributions_dsnd/__init__.py
distributions_dsnd.egg-info/PKG-INFO
distributions_dsnd.egg-info/SOURCES.txt
distributions_dsnd.egg-info/dependency_links.txt
distributions_dsnd.egg-info/not-zip-safe
distributions_dsnd.egg-info/top_level.txt